LICENSE
MANIFEST.in
README.rst
setup.py
vingd/__init__.py
vingd/client.py
vingd/exceptions.py
vingd/response.py
vingd/util.py
vingd.egg-info/PKG-INFO
vingd.egg-info/SOURCES.txt
vingd.egg-info/dependency_links.txt
vingd.egg-info/top_level.txt