Metadata-Version: 1.1
Name: vingd
Version: 0.1
Summary: Vingd API interface client.
Home-page: https://github.com/vingd/vingd-api-python
Author: Radomir Stevanovic
Author-email: radomir@vingd.com
License: MIT
Platform: UNKNOWN
Classifier: Development Status :: 5 - Production/Stable
Classifier: Intended Audience :: Developers
Classifier: Programming Language :: Python
Classifier: License :: OSI Approved :: MIT License
Classifier: Operating System :: OS Independent
Classifier: Topic :: Internet
Classifier: Topic :: Office/Business :: Financial
Classifier: Topic :: Software Development :: Libraries :: Python Modules
